<Vocab id="c0e4ca89-6c3c-49f1-a245-39115a3bd3f9" word="bibliographic" type="short" status="pending">
  <Topics>
    <Topic id="__UUID__" value="..." />
  </Topics>
  <Professions>
    <Profession id="__UUID__" value="..." />
  </Professions>
  <Pronunciations>
    <Pronunciation id="__UUID__" ipa="..." vi_ipa="...">
      <Audios>
        <Audio type="male_normal" value="..." />
        <Audio type="male_slow" value="..." />
        <Audio type="female_normal" value="..." />
        <Audio type="female_slow" value="..." />
      </Audios>
      <Meanings>
        <Meaning id="__UUID__" type="...">
          <Vi>...</Vi>
          <En>...</En>
          <Example>...</Example>
        </Meaning>
      </Meanings>
      <Situations>
        <Situation id="__UUID__">...</Situation>
      </Situations>
    </Pronunciation>
  </Pronunciations>
</Vocab>