<Vocab id="380bd2de-9884-41c0-89c3-03d5ca754943" word="don" type="short" status="pending">
  <Topics>
    <Topic id="__UUID__" value="..." />
  </Topics>
  <Professions>
    <Profession id="__UUID__" value="..." />
  </Professions>
  <Pronunciations>
    <Pronunciation id="__UUID__" ipa="..." vi_ipa="...">
      <Audios>
        <Audio type="male_normal" value="..." />
        <Audio type="male_slow" value="..." />
        <Audio type="female_normal" value="..." />
        <Audio type="female_slow" value="..." />
      </Audios>
      <Meanings>
        <Meaning id="__UUID__" type="...">
          <Vi>...</Vi>
          <En>...</En>
          <Example>...</Example>
        </Meaning>
      </Meanings>
      <Situations>
        <Situation id="__UUID__">
          <Vi>...</Vi>
          <En>...</En>
        </Situation>
      </Situations>
    </Pronunciation>
  </Pronunciations>
</Vocab>