<Vocab id="9fa918af-a38c-459e-8229-0a2d14862d3f" word="kay" type="short" status="pending">
  <Topics>
    <Topic id="__UUID__" value="..." />
  </Topics>
  <Professions>
    <Profession id="__UUID__" value="..." />
  </Professions>
  <Pronunciations>
    <Pronunciation id="__UUID__" ipa="..." vi_ipa="...">
      <Audios>
        <Audio type="male_normal" value="..." />
        <Audio type="male_slow" value="..." />
        <Audio type="female_normal" value="..." />
        <Audio type="female_slow" value="..." />
      </Audios>
      <Meanings>
        <Meaning id="__UUID__" type="...">
          <Vi>...</Vi>
          <En>...</En>
          <Example>...</Example>
        
        <IsArchaic>false</IsArchaic>
        
        <Situations>
          <Situation id="__UUID__">
            <Vi>...</Vi>
            <En>...</En>
          </Situation>
        </Situations>
        </Meaning>
      </Meanings>
    </Pronunciation>
  </Pronunciations>
</Vocab>