<Vocab id="a534b680-8403-44ef-b623-a158e597a1f0" word="shaped" type="short" status="pending">
  <Topics>
    <Topic id="__UUID__" value="..." />
  </Topics>
  <Professions>
    <Profession id="__UUID__" value="..." />
  </Professions>
  <Pronunciations>
    <Pronunciation id="__UUID__" ipa="..." vi_ipa="...">
      <Audios>
        <Audio type="male_normal" value="..." />
        <Audio type="male_slow" value="..." />
        <Audio type="female_normal" value="..." />
        <Audio type="female_slow" value="..." />
      </Audios>
      <Meanings>
        <Meaning id="__UUID__" type="...">
          <Vi>...</Vi>
          <En>...</En>
          <Example>...</Example>
        
        <Situations>
          <Situation id="__UUID__">
            <Vi>...</Vi>
            <En>...</En>
          </Situation>
        </Situations>
        </Meaning>
      </Meanings>
    </Pronunciation>
  </Pronunciations>
</Vocab>