<Vocab id="7e634a88-c691-4b31-bbf5-fa672d4e04b3" word="lab" type="short" status="done">
  <Topics>
    <Topic id="fe74617f-40da-495e-b91e-21b2c2ce575f" value="Science &amp; Education" />
  </Topics>
  <Professions>
    <Profession id="817952f7-3153-46b4-9da1-e4227c25c232" value="Scientist" />
    <Profession id="a20cec2e-0225-48e3-898f-67b26cf629b2" value="Medical Technician" />
    <Profession id="f7c73974-50e8-4825-991f-586e1ac97e10" value="Researcher" />
  </Professions>
  <Pronunciations>
    <Pronunciation id="f9b5a1f1-7870-4eb1-a5e6-631feb36544a" ipa="/læb/" vi_ipa="lẹp">
      <Audios>
        <Audio type="male_normal" value="" />
        <Audio type="male_slow" value="" />
        <Audio type="female_normal" value="" />
        <Audio type="female_slow" value="" />
      </Audios>
      <Meanings>
        <Meaning id="c77af04e-12a0-4bb0-957c-a538d35f23f7" type="Noun">
          <Vi>phòng thí nghiệm</Vi>
          <En>A room or building equipped for scientific experiments, research, or teaching.</En>
          <Example>The students conducted a chemistry experiment in the lab.</Example>
          <IsArchaic>false</IsArchaic>
          <Situations>
            <Situation id="0c142afc-0cac-4b3e-9fe9-bbc878c68cd6">
              <Vi>Một không gian chuyên dụng để thực hiện các thí nghiệm khoa học.</Vi>
              <En>A dedicated space where scientific experiments are performed.</En>
            </Situation>
            <Situation id="cec9f94b-d7da-4f74-b9e8-22b75fe906b4">
              <Vi>Cơ sở y tế nơi xét nghiệm mẫu máu hoặc mô.</Vi>
              <En>A medical facility where blood or tissue samples are tested.</En>
            </Situation>
          </Situations>
        </Meaning>
      </Meanings>
    </Pronunciation>
  </Pronunciations>
</Vocab>