<Vocab id="55bbc328-3697-4343-8e64-18342fa2b41d" word="lower" type="short" status="done">
  <Topics>
    <Topic id="193a03b9-8caa-44e0-84c4-7e39ae136655" value="General" />
  </Topics>
  <Professions>
    <Profession id="1c3cf42d-a41a-4da0-a438-76d0f9e4cc44" value="General" />
  </Professions>
  <Pronunciations>
    <Pronunciation id="9d228c00-41cb-438c-b580-ec9416214fd9" ipa="/ˈloʊ.ɚ/" vi_ipa="lơ-ơ">
      <Audios>
        <Audio type="male_normal" value="" />
        <Audio type="male_slow" value="" />
        <Audio type="female_normal" value="" />
        <Audio type="female_slow" value="" />
      </Audios>
      <Meanings>
        <Meaning id="d6f4996e-3daf-494a-a4bd-7b9a115ce6a3" type="Verb">
          <Vi>hạ, giảm, đặt thấp hơn</Vi>
          <En>to move something down; to reduce something in amount, degree, or intensity</En>
          <Example>She lowered the volume of the music.</Example>
          <IsArchaic>false</IsArchaic>
          <Situations>
            <Situation id="264fd24f-ca1b-4fd4-b0d6-a14f4595b8ad">
              <Vi>Giảm âm lượng, hạ cửa sổ xe, hoặc đặt vật xuống thấp hơn vị trí hiện tại.</Vi>
              <En>Reducing volume, lowering a car window, or moving an object to a lower position.</En>
            </Situation>
          </Situations>
        </Meaning>
        <Meaning id="8b285ab1-e7ed-499f-83fb-1ffbbe955edb" type="Adjective">
          <Vi>thấp hơn, dưới, thấp</Vi>
          <En> situated or directed downward; of lesser height or intensity</En>
          <Example>He sat in the lower seat to be closer to the ground.</Example>
          <IsArchaic>false</IsArchaic>
          <Situations>
            <Situation id="063d0733-d03f-423a-935c-c023239f6293">
              <Vi>Mô tả vị trí thấp hơn (ví dụ: tầng dưới, ghế thấp, mức độ thấp).</Vi>
              <En>Describing a position, rank, or level that is physically or figuratively lower.</En>
            </Situation>
          </Situations>
        </Meaning>
        <Meaning id="4ee09450-69f7-4239-8658-0fa09d7d48f5" type="Noun">
          <Vi>phần thấp hơn, phần dưới</Vi>
          <En>the lower part or position of something</En>
          <Example>The lower half of the painting is faded.</Example>
          <IsArchaic>false</IsArchaic>
          <Situations>
            <Situation id="9c884780-18b7-43eb-978f-7c91af8753e7">
              <Vi>Chỉ phần dưới của cơ thể, vật thể, hoặc cấu trúc.</Vi>
              <En>Referring to the bottom portion of a body, object, or structure.</En>
            </Situation>
          </Situations>
        </Meaning>
      </Meanings>
    </Pronunciation>
    <Pronunciation id="57524bcf-5213-4cfc-b4c7-8a7f7d296dac" ipa="/ˈloʊ.ɚ/" vi_ipa="lơ-ơ">
      <Audios>
        <Audio type="male_normal" value="" />
        <Audio type="male_slow" value="" />
        <Audio type="female_normal" value="" />
        <Audio type="female_slow" value="" />
      </Audios>
      <Meanings>
        <Meaning id="00d1a2fb-8066-4ba9-bcd3-b240fc99c8ed" type="Verb">
          <Vi>giảm (giá), làm giảm (yêu cầu, kỳ vọng)</Vi>
          <En>to reduce the price, expectations, or demands</En>
          <Example>The company lowered its price to attract more customers.</Example>
          <IsArchaic>false</IsArchaic>
          <Situations>
            <Situation id="4f8a6f87-0d76-48ca-a3c7-d6816eff7ac8">
              <Vi>Giảm giá bán, giảm kỳ vọng, hoặc hạ tiêu chuẩn trong kinh doanh hoặc đàm phán.</Vi>
              <En>Reducing price, expectations, or standards in business or negotiation contexts.</En>
            </Situation>
          </Situations>
        </Meaning>
      </Meanings>
    </Pronunciation>
  </Pronunciations>
</Vocab>